flight_sun/__init__.py
flight_sun/flight.py
flight_sun/geo.py
flight_sun/visualisation.py
flight_sun-0.1.0.dist-info/LICENSE
flight_sun-0.1.0.dist-info/METADATA
flight_sun-0.1.0.dist-info/WHEEL
flight_sun-0.1.0.dist-info/top_level.txt
flight_sun-0.1.0.dist-info/RECORD
