Metadata-Version: 2.1
Name: flight-sun
Version: 0.1.0
Summary: Calculate the sun position during a flight
Author-email: James Baird <j.baird94@gmail.com>
License: MIT License
Project-URL: repository, https://github.com/bairdj/flight_sun
License-File: LICENSE
Requires-Dist: airportsdata
Requires-Dist: skyfield
